[
  {
    "geracao": 1,
    "melhor": 0.5,
    "media": 0.125
  },
  {
    "geracao": 2,
    "melhor": 0.5,
    "media": 0.125
  },
  {
    "geracao": 3,
    "melhor": 0.5,
    "media": 0.125
  },
  {
    "geracao": 4,
    "melhor": 0.5,
    "media": 0.125
  },
  {
    "geracao": 5,
    "melhor": 0.5,
    "media": 0.125
  },
  {
    "geracao": 6,
    "melhor": 0.5,
    "media": 0.125
  },
  {
    "geracao": 7,
    "melhor": 0.5,
    "media": 0.125
  },
  {
    "geracao": 8,
    "melhor": 0.5,
    "media": 0.125
  },
  {
    "geracao": 9,
    "melhor": 0.5,
    "media": 0.125
  },
  {
    "geracao": 10,
    "melhor": 0.5,
    "media": 0.125
  }
]